dcw/__init__.py
dcw/cli/__init__.py
dcw/cli/pipeline.py
dcw/etl/__init__.py
dcw/etl/demo_pipeline.py
dcw/etl/extract.py
dcw/etl/load.py
dcw/etl/pipeline.py
dcw/etl/transform.py
dcw/logging.py
dcw/storage/__init__.py
dcw/storage/backend.py
dcw/storage/factory.py
dcw/storage/filesystem.py
dcw/storage/gcp.py
dcw/storage/layout.py
dcw/system.py
dcw/timing.py
dcw-0.0.11.dist-info/LICENSE
dcw-0.0.11.dist-info/METADATA
dcw-0.0.11.dist-info/WHEEL
dcw-0.0.11.dist-info/entry_points.txt
dcw-0.0.11.dist-info/RECORD
