Metadata-Version: 2.1
Name: dcw
Version: 0.0.11
Summary: 
Home-page: https://github.com/derekwisong/dcw
License: GPL-3.0-only
Keywords: data,pipeline,data pipeline,data engineering,data science,data management,data quality
Author: Derek Wisong
Author-email: derekwisong@gmail.com
Requires-Python: >=3.10,<4.0
Classifier: License :: OSI Approved :: GNU General Public License v3 (GPLv3)
Classifier: Programming Language :: Python :: 3
Classifier: Programming Language :: Python :: 3.10
Classifier: Programming Language :: Python :: 3.11
Classifier: Programming Language :: Python :: 3.12
Requires-Dist: fastparquet (>=2023.10.1,<2024.0.0)
Requires-Dist: google-cloud-storage (>=2.14.0,<3.0.0)
Requires-Dist: pandas (>=2.1.3,<3.0.0)
Requires-Dist: pyarrow (>=14.0.2,<15.0.0)
Requires-Dist: pydantic (>=2.5.2,<3.0.0)
Requires-Dist: pytest (>=7.4.3,<8.0.0)
Requires-Dist: python-snappy (>=0.6.1,<0.7.0)
Requires-Dist: requests (>=2.31.0,<3.0.0)
Requires-Dist: streamz (>=0.6.4,<0.7.0)
Requires-Dist: tabulate (>=0.9.0,<0.10.0)
Project-URL: Documentation, https://derekwisong.github.io/dcw
Project-URL: Repository, https://github.com/derekwisong/dcw
